[
    {
      "title": "Clothing Store Simulator",
      "desc": "Are you ready to shape fashion world? Make a brand deal, order products, fill the aisles, dress the mannequins and start selling. Dresses, shirts, coats, pants, nightwear, underwear, shoes and more are waiting for you.",
      "imgheader": "https://cdn.cloudflare.steamstatic.com/steam/apps/2923390/header.jpg",
      "imgbg": "https://cdn.cloudflare.steamstatic.com/steam/apps/2923390/page_bg_generated_v6b.jpg",
      "downloadlink": "https://cdn3.filehaus.su/files/1731358507_19563/Clothing_Store_Simulator.7z",
      "storepage": "https://store.steampowered.com/app/2923390/",
      "patchnotes": "https://steamdb.info/app/2923390/patchnotes/",
      "quota": "Files by ME,\nCrack by Mr_Goldberg,\nSteamless by atom0s",
      "version": "16311788",
      "size": "1.6GB"
    },
    {
      "title": "Mad Games Tycoon 2",
      "desc": "Start your own game development studio in 1976. Build your own offices, production facilities and server rooms. Develop the games of your dreams and produce the next next-gen console. Rise from a small garage company to a huge corporation.",
      "imgheader": "https://cdn.cloudflare.steamstatic.com/steam/apps/1342330/header.jpg",
      "imgbg": "https://cdn.cloudflare.steamstatic.com/steam/apps/1342330/page_bg_generated_v6b.jpg",
      "downloadlink": "https://cdn5.filehaus.su/files/1731360539_74727/Mad_Games_Tycoon_2.7z",
      "storepage": "https://store.steampowered.com/app/1342330/",
      "patchnotes": "https://steamdb.info/app/1342330/patchnotes/",
      "quota": "Files by GodPigeon,\nUpdate by Mart1z\nCrack by Mr_Goldberg,\nSteamless by atom0s",
      "version": "14182136",
      "size": "309MB"
    }
  ]
  